eoftoolkit/__init__.py
eoftoolkit/analysis/__init__.py
eoftoolkit/analysis/reconstruction.py
eoftoolkit/analysis/svd.py
eoftoolkit/analysis/validation.py
eoftoolkit/core/__init__.py
eoftoolkit/core/exceptions.py
eoftoolkit/core/processor.py
eoftoolkit/core/processor.py.backup
eoftoolkit/core/utils.py
eoftoolkit/geo/__init__.py
eoftoolkit/geo/grid.py
eoftoolkit/geo/projections.py
eoftoolkit/io/__init__.py
eoftoolkit/io/reader.py
eoftoolkit/io/sorter.py
eoftoolkit/io/writer.py
eoftoolkit/processor/__init__.py
eoftoolkit/processor/dimensions.py
eoftoolkit/processor/flattener.py
eoftoolkit/processor/identification.py
eoftoolkit/processor/masking.py
eoftoolkit/processor/reshaper.py
eoftoolkit/processor/stacker.py
eoftoolkit/version.py
eoftoolkit/visualization/__init__.py
eoftoolkit/visualization/base_maps.py
eoftoolkit/visualization/eof_plots.py
eoftoolkit/visualization/error_plots.py
eoftoolkit/visualization/pc_plots.py
eoftoolkit/visualization/plotting_improvements.py
eoftoolkit/visualization/reconstruction_plots.py
eoftoolkit/visualization/spatial.py
eoftoolkit-0.1.0.dist-info/LICENSE
eoftoolkit-0.1.0.dist-info/METADATA
eoftoolkit-0.1.0.dist-info/WHEEL
eoftoolkit-0.1.0.dist-info/RECORD
