Metadata-Version: 2.3
Name: eoftoolkit
Version: 0.1.0
Summary: A comprehensive Python toolkit for Empirical Orthogonal Function (EOF) analysis
License: MIT
Keywords: EOF,climate,meteorology,oceanography,data-analysis,geoscience
Author: Mohammad Kord
Author-email: mohammadkord99@gmail.com
Maintainer: Mohammad Kord
Maintainer-email: mohammadkord99@gmail.com
Requires-Python: >=3.8,<4.0
Classifier: Development Status :: 4 - Beta
Classifier: Intended Audience :: Science/Research
Classifier: License :: OSI Approved :: MIT License
Classifier: Operating System :: OS Independent
Classifier: Programming Language :: Python :: 3
Classifier: Programming Language :: Python :: 3.8
Classifier: Programming Language :: Python :: 3.9
Classifier: Programming Language :: Python :: 3.10
Classifier: Programming Language :: Python :: 3.11
Classifier: Programming Language :: Python :: 3.12
Classifier: Programming Language :: Python :: 3.13
Classifier: Topic :: Scientific/Engineering
Classifier: Topic :: Scientific/Engineering :: Atmospheric Science
Classifier: Topic :: Scientific/Engineering :: GIS
Classifier: Topic :: Scientific/Engineering :: Mathematics
Provides-Extra: all
Provides-Extra: plotting
Requires-Dist: basemap (>=1.3.0,<2.0.0) ; extra == "plotting" or extra == "all"
Requires-Dist: cartopy (>=0.20.0,<0.21.0) ; extra == "plotting" or extra == "all"
Requires-Dist: matplotlib (>=3.5.0,<4.0.0) ; extra == "plotting" or extra == "all"
Requires-Dist: netCDF4 (>=1.5.0,<2.0.0)
Requires-Dist: numpy (>=1.20.0,<2.0.0)
Requires-Dist: pandas (>=1.3.0,<2.0.0)
Requires-Dist: scipy (>=1.7.0,<2.0.0)
Project-URL: Bug Tracker, https://github.com/Mkord99/EOFtoolkit/issues
Project-URL: Documentation, https://github.com/Mkord99/EOFtoolkit
Project-URL: Homepage, https://github.com/Mkord99/EOFtoolkit
Project-URL: Repository, https://github.com/Mkord99/EOFtoolkit
Project-URL: Source Code, https://github.com/Mkord99/EOFtoolkit
